{
  "0008983": {
    "doc_info": {
      "title": "8983_Boeing_secures_11bn_of_aircraft_deals",
      "url": "http://en.wikinews.org/wiki/Boeing_secures_$11bn_of_aircraft_deals"
    },
    "sentences": {
      "00": {
        "text": "ボーイング、110億ドルの航空機取引を確保",
        "mention_ids": [
          "M017"
        ]
      },
      "01": {
        "text": "2005年4月27日",
        "mention_ids": []
      },
      "02": {
        "text": "アメリカの航空機777がヒースロー空港に着陸ボーイングは、新型航空機の2つの大型発注を確保しました。",
        "mention_ids": [
          "M001",
          "M002",
          "M018",
          "M019"
        ]
      },
      "03": {
        "text": "エア・カナダは新型旅客機を60億米ドルで発注し、エア・インディアはさらに70億米ドルの契約を締結しました。",
        "mention_ids": [
          "M003",
          "M004",
          "M005"
        ]
      },
      "04": {
        "text": "エア・カナダの契約には、777を18機と新型の中型長距離787ドリームライナー14機の確定発注が含まれています。",
        "mention_ids": [
          "M006",
          "M014"
        ]
      },
      "05": {
        "text": "オプションには、さらに18機の777と46機の787が含まれています。",
        "mention_ids": [
          "M013",
          "M015"
        ]
      },
      "06": {
        "text": "エア・インディアの注文は、50機の787で68億米ドル相当です。",
        "mention_ids": [
          "M010",
          "M016"
        ]
      },
      "07": {
        "text": "エア・インディアは、新しい燃料効率の高い旅客機は年間3億米ドルの燃料を節約できると述べ、一方エア・カナダは既存の767に比べて30%の燃料節約になると見積もっています。",
        "mention_ids": [
          "M101"
        ]
      },
      "08": {
        "text": "エア・インディアはまた、787が同サイズのエアバスA330に比べて20席多いことが決め手となったと述べています。",
        "mention_ids": [
          "M108"
        ]
      },
      "09": {
        "text": "大韓航空も今月初めにドリームライナーを20機購入しました。",
        "mention_ids": [
          "M093"
        ]
      },
      "10": {
        "text": "ボーイングは現在、787の合計237機の受注と確約を取っています。",
        "mention_ids": [
          "M090",
          "M121"
        ]
      },
      "11": {
        "text": "ボーイング777は、ボーイング民間航空機によって製造された長距離ワイドボディ双発旅客機のファミリーです。",
        "mention_ids": [
          "M094",
          "M167"
        ]
      },
      "12": {
        "text": "それは305～550名の乗客を乗せ、航続距離は5,600～8,870海里(10,400～16,400km)です。",
        "mention_ids": [
          "M081"
        ]
      },
      "13": {
        "text": "777の初飛行は1994年でした。",
        "mention_ids": [
          "M112"
        ]
      },
      "14": {
        "text": "ボーイング787、またはドリームライナーは、ボーイング民間航空機によって現在開発中で、2008年に就航予定の中型旅客機です。",
        "mention_ids": [
          "M084",
          "M122"
        ]
      },
      "15": {
        "text": "それは、座席構成に応じて200人から350人の乗客を運ぶことができ、初期の旅客機よりも燃料効率が高くなります。",
        "mention_ids": [
          "M103"
        ]
      },
      "16": {
        "text": "さらに、それは、その構造の大部分に複合材料を使用した最初の主要旅客機となります。",
        "mention_ids": [
          "M078",
          "M086"
        ]
      }
    },
    "mentions": {
      "M001": {
        "sentence_id": "02",
        "span": [
          22,
          27
        ],
        "text": "ボーイング",
        "entity_type": null,
        "entity_id": "E150"
      },
      "M002": {
        "sentence_id": "02",
        "span": [
          0,
          11
        ],
        "text": "アメリカの航空機777",
        "entity_type": null,
        "entity_id": null
      },
      "M003": {
        "sentence_id": "03",
        "span": [
          0,
          6
        ],
        "text": "エア・カナダ",
        "entity_type": null,
        "entity_id": "E166"
      },
      "M004": {
        "sentence_id": "03",
        "span": [
          7,
          12
        ],
        "text": "新型旅客機",
        "entity_type": null,
        "entity_id": "E164"
      },
      "M005": {
        "sentence_id": "03",
        "span": [
          24,
          32
        ],
        "text": "エア・インディア",
        "entity_type": null,
        "entity_id": "E161"
      },
      "M006": {
        "sentence_id": "04",
        "span": [
          0,
          6
        ],
        "text": "エア・カナダ",
        "entity_type": null,
        "entity_id": "E166"
      },
      "M010": {
        "sentence_id": "06",
        "span": [
          0,
          8
        ],
        "text": "エア・インディア",
        "entity_type": null,
        "entity_id": "E161"
      },
      "M013": {
        "sentence_id": "05",
        "span": [
          0,
          5
        ],
        "text": "オプション",
        "entity_type": null,
        "entity_id": "E151"
      },
      "M014": {
        "sentence_id": "04",
        "span": [
          12,
          42
        ],
        "text": "777を18機と新型の中型長距離787ドリームライナー14機",
        "entity_type": null,
        "entity_id": "E068"
      },
      "M015": {
        "sentence_id": "05",
        "span": [
          8,
          26
        ],
        "text": "さらに18機の777と46機の787",
        "entity_type": null,
        "entity_id": "E069"
      },
      "M016": {
        "sentence_id": "06",
        "span": [
          13,
          20
        ],
        "text": "50機の787",
        "entity_type": null,
        "entity_id": "E070"
      },
      "M017": {
        "sentence_id": "00",
        "span": [
          0,
          5
        ],
        "text": "ボーイング",
        "entity_type": null,
        "entity_id": "E150"
      },
      "M018": {
        "sentence_id": "02",
        "span": [
          29,
          34
        ],
        "text": "新型航空機",
        "entity_type": null,
        "entity_id": "E164"
      },
      "M019": {
        "sentence_id": "02",
        "span": [
          12,
          19
        ],
        "text": "ヒースロー空港",
        "entity_type": null,
        "entity_id": "E145"
      },
      "M078": {
        "sentence_id": "16",
        "span": [
          4,
          6
        ],
        "text": "それ",
        "entity_type": null,
        "entity_id": "E154"
      },
      "M081": {
        "sentence_id": "12",
        "span": [
          0,
          2
        ],
        "text": "それ",
        "entity_type": null,
        "entity_id": "E142"
      },
      "M084": {
        "sentence_id": "14",
        "span": [
          22,
          27
        ],
        "text": "ボーイング",
        "entity_type": null,
        "entity_id": "E150"
      },
      "M086": {
        "sentence_id": "16",
        "span": [
          8,
          10
        ],
        "text": "その",
        "entity_type": null,
        "entity_id": "E154"
      },
      "M090": {
        "sentence_id": "10",
        "span": [
          0,
          5
        ],
        "text": "ボーイング",
        "entity_type": null,
        "entity_id": "E150"
      },
      "M093": {
        "sentence_id": "09",
        "span": [
          10,
          18
        ],
        "text": "ドリームライナー",
        "entity_type": null,
        "entity_id": "E154"
      },
      "M094": {
        "sentence_id": "11",
        "span": [
          0,
          8
        ],
        "text": "ボーイング777",
        "entity_type": null,
        "entity_id": "E142"
      },
      "M101": {
        "sentence_id": "07",
        "span": [
          10,
          23
        ],
        "text": "新しい燃料効率の高い旅客機",
        "entity_type": null,
        "entity_id": "E154"
      },
      "M103": {
        "sentence_id": "15",
        "span": [
          0,
          2
        ],
        "text": "それ",
        "entity_type": null,
        "entity_id": "E154"
      },
      "M108": {
        "sentence_id": "08",
        "span": [
          12,
          15
        ],
        "text": "787",
        "entity_type": null,
        "entity_id": "E154"
      },
      "M112": {
        "sentence_id": "13",
        "span": [
          0,
          3
        ],
        "text": "777",
        "entity_type": null,
        "entity_id": "E142"
      },
      "M121": {
        "sentence_id": "10",
        "span": [
          9,
          12
        ],
        "text": "787",
        "entity_type": null,
        "entity_id": "E154"
      },
      "M122": {
        "sentence_id": "14",
        "span": [
          0,
          20
        ],
        "text": "ボーイング787、またはドリームライナー",
        "entity_type": null,
        "entity_id": "E154"
      },
      "M167": {
        "sentence_id": "11",
        "span": [
          10,
          15
        ],
        "text": "ボーイング",
        "entity_type": null,
        "entity_id": "E150"
      }
    },
    "entities": {
      "E068": {
        "member_mention_ids": [
          "M014"
        ],
        "entity_type": "PRO",
        "has_enwiki_ref": false,
        "has_jawiki_ref": false,
        "has_wikidata_ref": false,
        "has_dbpedia_ref": false,
        "ref_urls": {}
      },
      "E069": {
        "member_mention_ids": [
          "M015"
        ],
        "entity_type": "PRO",
        "has_enwiki_ref": false,
        "has_jawiki_ref": false,
        "has_wikidata_ref": false,
        "has_dbpedia_ref": false,
        "ref_urls": {}
      },
      "E070": {
        "member_mention_ids": [
          "M016"
        ],
        "entity_type": "PRO",
        "has_enwiki_ref": false,
        "has_jawiki_ref": false,
        "has_wikidata_ref": false,
        "has_dbpedia_ref": false,
        "ref_urls": {}
      },
      "E142": {
        "member_mention_ids": [
          "M081",
          "M094",
          "M112"
        ],
        "removed_mention_ids": [
          "M009",
          "M109",
          "M007"
        ],
        "entity_type": "PRO",
        "has_enwiki_ref": true,
        "has_jawiki_ref": true,
        "has_wikidata_ref": true,
        "has_dbpedia_ref": true,
        "ref_urls": {
          "dbpedia": "http://dbpedia.org/page/Boeing_777",
          "en.wikipedia": "https://en.wikipedia.org/wiki/Boeing_777",
          "wikidata": "http://www.wikidata.org/entity/Q6425",
          "ja.wikipedia": "https://ja.wikipedia.org/wiki/%E3%83%9C%E3%83%BC%E3%82%A4%E3%83%B3%E3%82%B0777"
        }
      },
      "E145": {
        "member_mention_ids": [
          "M019"
        ],
        "entity_type": "LOC",
        "has_enwiki_ref": true,
        "has_jawiki_ref": true,
        "has_wikidata_ref": true,
        "has_dbpedia_ref": true,
        "ref_urls": {
          "dbpedia": "http://dbpedia.org/page/London_Heathrow_Airport",
          "dbpedia:orig": "http://dbpedia.org/page/London_Heathrow_Airport",
          "en.wikipedia": "https://en.wikipedia.org/wiki/Heathrow_Airport",
          "wikidata": "http://www.wikidata.org/entity/Q8691",
          "ja.wikipedia": "https://ja.wikipedia.org/wiki/%E3%83%AD%E3%83%B3%E3%83%89%E3%83%B3%E3%83%BB%E3%83%92%E3%83%BC%E3%82%B9%E3%83%AD%E3%83%BC%E7%A9%BA%E6%B8%AF"
        }
      },
      "E150": {
        "member_mention_ids": [
          "M001",
          "M017",
          "M084",
          "M090",
          "M167"
        ],
        "entity_type": "ORG",
        "has_enwiki_ref": true,
        "has_jawiki_ref": true,
        "has_wikidata_ref": true,
        "has_dbpedia_ref": true,
        "ref_urls": {
          "dbpedia": "http://dbpedia.org/page/Boeing",
          "en.wikipedia": "https://en.wikipedia.org/wiki/Boeing",
          "wikidata": "http://www.wikidata.org/entity/Q66",
          "ja.wikipedia": "https://ja.wikipedia.org/wiki/%E3%83%9C%E3%83%BC%E3%82%A4%E3%83%B3%E3%82%B0"
        }
      },
      "E151": {
        "member_mention_ids": [
          "M013"
        ],
        "entity_type": "FIN",
        "has_enwiki_ref": false,
        "has_jawiki_ref": false,
        "has_wikidata_ref": false,
        "has_dbpedia_ref": false,
        "ref_urls": {}
      },
      "E154": {
        "member_mention_ids": [
          "M078",
          "M086",
          "M093",
          "M101",
          "M103",
          "M108",
          "M121",
          "M122"
        ],
        "removed_mention_ids": [
          "M011",
          "M012",
          "M008"
        ],
        "entity_type": "PRO",
        "has_enwiki_ref": true,
        "has_jawiki_ref": true,
        "has_wikidata_ref": true,
        "has_dbpedia_ref": true,
        "ref_urls": {
          "dbpedia": "http://dbpedia.org/page/Boeing_787_Dreamliner",
          "en.wikipedia": "https://en.wikipedia.org/wiki/Boeing_787_Dreamliner",
          "wikidata": "http://www.wikidata.org/entity/Q6428",
          "ja.wikipedia": "https://ja.wikipedia.org/wiki/%E3%83%9C%E3%83%BC%E3%82%A4%E3%83%B3%E3%82%B0787"
        }
      },
      "E161": {
        "member_mention_ids": [
          "M005",
          "M010"
        ],
        "entity_type": "ORG",
        "has_enwiki_ref": true,
        "has_jawiki_ref": true,
        "has_wikidata_ref": true,
        "has_dbpedia_ref": true,
        "ref_urls": {
          "dbpedia": "http://dbpedia.org/page/Air_India",
          "en.wikipedia": "https://en.wikipedia.org/wiki/Air_India",
          "wikidata": "http://www.wikidata.org/entity/Q69906",
          "ja.wikipedia": "https://ja.wikipedia.org/wiki/%E3%82%A8%E3%82%A2%E3%83%BB%E3%82%A4%E3%83%B3%E3%83%87%E3%82%A3%E3%82%A2"
        }
      },
      "E164": {
        "member_mention_ids": [
          "M004",
          "M018"
        ],
        "entity_type": "PRO",
        "has_enwiki_ref": false,
        "has_jawiki_ref": false,
        "has_wikidata_ref": false,
        "has_dbpedia_ref": false,
        "ref_urls": {}
      },
      "E166": {
        "member_mention_ids": [
          "M003",
          "M006"
        ],
        "entity_type": "ORG",
        "has_enwiki_ref": true,
        "has_jawiki_ref": true,
        "has_wikidata_ref": true,
        "has_dbpedia_ref": true,
        "ref_urls": {
          "dbpedia": "http://dbpedia.org/page/Air_Canada",
          "en.wikipedia": "https://en.wikipedia.org/wiki/Air_Canada",
          "wikidata": "http://www.wikidata.org/entity/Q185339",
          "ja.wikipedia": "https://ja.wikipedia.org/wiki/%E3%82%A8%E3%82%A2%E3%83%BB%E3%82%AB%E3%83%8A%E3%83%80"
        }
      },
      "E170": {
        "member_mention_ids": [],
        "removed_mention_ids": [
          "M074"
        ],
        "entity_type": "PRO",
        "has_enwiki_ref": false,
        "has_jawiki_ref": false,
        "has_wikidata_ref": false,
        "has_dbpedia_ref": false,
        "ref_urls": {}
      },
      "E171": {
        "member_mention_ids": [],
        "removed_mention_ids": [
          "M077"
        ],
        "entity_type": "PRO",
        "has_enwiki_ref": false,
        "has_jawiki_ref": false,
        "has_wikidata_ref": false,
        "has_dbpedia_ref": false,
        "ref_urls": {}
      },
      "E172": {
        "member_mention_ids": [],
        "removed_mention_ids": [
          "M076"
        ],
        "entity_type": "PRO",
        "has_enwiki_ref": false,
        "has_jawiki_ref": false,
        "has_wikidata_ref": false,
        "has_dbpedia_ref": false,
        "ref_urls": {}
      }
    }
  }
}